flamyngo/__init__.py
flamyngo/app.py
flamyngo/flm.py
flamyngo/views.py
flamyngo/static/index.css
flamyngo/static/plot.css
flamyngo/static/style.css
flamyngo/static/summary.css
flamyngo/static/js/bower.json
flamyngo/static/js/package.json
flamyngo/static/js/renderjson.js
flamyngo/templates/doc.html
flamyngo/templates/index.html
flamyngo/templates/layout.html
flamyngo/templates/plot.html
flamyngo-1.2.1.dist-info/LICENSE
flamyngo-1.2.1.dist-info/METADATA
flamyngo-1.2.1.dist-info/WHEEL
flamyngo-1.2.1.dist-info/entry_points.txt
flamyngo-1.2.1.dist-info/top_level.txt
flamyngo-1.2.1.dist-info/RECORD
