Metadata-Version: 2.1
Name: flamyngo
Version: 1.2.1
Summary: Flamyngo is a customizable Flask frontend for MongoDB.
Home-page: https://github.com/materialsvirtuallab/flamyngo
Author: Shyue Ping Ong
Author-email: ongsp@eng.ucsd.edu
Maintainer: Shyue Ping Ong
Maintainer-email: ongsp@eng.ucsd.edu
License: BSD
Keywords: flask,web,frontend,gui,MongoDB
Platform: UNKNOWN
Classifier: Programming Language :: Python :: 3
Classifier: Programming Language :: Python :: 3.8
Classifier: Programming Language :: Python :: 3.9
Classifier: Programming Language :: Python :: 3.10
Classifier: Development Status :: 4 - Beta
Classifier: License :: OSI Approved :: MIT License
Classifier: Operating System :: OS Independent
License-File: LICENSE
Requires-Dist: flask
Requires-Dist: pyyaml
Requires-Dist: monty (>=0.7.0)
Requires-Dist: pymongo
